__init__.py
bank_methods.py
open_methods.py
zip_functions.py
requestsbankrko-0.2.35.dist-info/licenses/LICENSE
requestsbankrko-0.2.35.dist-info/METADATA
requestsbankrko-0.2.35.dist-info/WHEEL
requestsbankrko-0.2.35.dist-info/top_level.txt
requestsbankrko-0.2.35.dist-info/RECORD
