Metadata-Version: 2.4
Name: requestsbankrko
Version: 0.2.35
Summary: Гарантированно успешные web-запросы в Банки РКО
Author-email: plp-kolyan <plp-kolyan@mail.ru>
License: Copyright (c) 2018 The Python Packaging Authority
Project-URL: Homepage, https://github.com/plp-kolyan/requestsbankrko
Classifier: Programming Language :: Python :: 3
Classifier: License :: OSI Approved :: MIT License
Classifier: Operating System :: OS Independent
Requires-Python: >=3.7
License-File: LICENSE
Requires-Dist: requestsgarant>=0.0.7
Requires-Dist: requests>=2.28
Requires-Dist: jsoncustom>=0.0.2
Requires-Dist: python-dotenv>=0.20.0
Dynamic: license-file
